pyBOT/__init__.py
pyBOT/app.py
pyBOT/framelessDragg.py
pyBOT/installer.py
pyBOT/myCMD.py
pyBOT/myHighlight.py
pyBOT/out.py
pyBOT/pyBOT.py
pyBOT/pyBOT2.py
pyBOT/pyBOTForm.py
pyBOT/pyThreads.py
pyBOT/pythonconsolewidget.py
pyBOT/res_rc.py
pyBOT/runner.py
pyBOT/sel2.py
pyBOT/seleniumApp.py
pyBOT/ss.py
pyBOT/syntax.py
pyBOT/tasks.py
pyBOT/utils.py
pyBOT_MDY-0.0.1.dist-info/DESCRIPTION.rst
pyBOT_MDY-0.0.1.dist-info/LICENSE.txt
pyBOT_MDY-0.0.1.dist-info/METADATA
pyBOT_MDY-0.0.1.dist-info/RECORD
pyBOT_MDY-0.0.1.dist-info/WHEEL
pyBOT_MDY-0.0.1.dist-info/dependency_links.txt
pyBOT_MDY-0.0.1.dist-info/entry_points.txt
pyBOT_MDY-0.0.1.dist-info/metadata.json
pyBOT_MDY-0.0.1.dist-info/top_level.txt
