Metadata-Version: 2.0
Name: pyBOT-MDY
Version: 0.0.1
Summary: Mi First Wheel package
Home-page: http://daemondev.com
Author: Richar Santiago Muñico Samaniego
Author-email: granlinux@gmail.com
License: GPL
Requires-Dist: flask
Requires-Dist: pymongo
Requires-Dist: pyqt5
Requires-Dist: pyqt5-tools
